autograd/__init__.py
autograd/function.py
autograd/module.py
autograd/optim.py
autograd/parameter.py
autograd/tensor.py
autograd/tensor_ops.py
autograd/Layers/Attention.py
autograd/Layers/Linear.py
autograd/Layers/__init__.py
tests/__init__.py
tests/test_tensor_add.py
tests/test_tensor_matmul.py
tests/test_tensor_mul.py
tests/test_tensor_sub.py
tests/test_tensor_sum.py
tests/test_tensor_transpose.py
Torch_Yottaxx-0.1.3.dist-info/LICENSE.md 
Torch_Yottaxx-0.1.3.dist-info/METADATA
Torch_Yottaxx-0.1.3.dist-info/WHEEL
Torch_Yottaxx-0.1.3.dist-info/top_level.txt
Torch_Yottaxx-0.1.3.dist-info/RECORD
