Metadata-Version: 2.1
Name: Torch-Yottaxx
Version: 0.1.3
Summary: a simple autograd library
Home-page: https://github.com/Yottaxx/YottaTorch
Author: Yotta
Author-email: xiaoz987@gmail.com
License: UNKNOWN
Platform: UNKNOWN
Classifier: Programming Language :: Python :: 3
Classifier: License :: OSI Approved :: MIT License
Classifier: Operating System :: OS Independent
Requires-Python: >=3.6
Requires-Dist: numpy
Requires-Dist: pytest
